esi_genoa_client/__init__.py
esi_genoa_client/api_client.py
esi_genoa_client/api_response.py
esi_genoa_client/configuration.py
esi_genoa_client/exceptions.py
esi_genoa_client/py.typed
esi_genoa_client/rest.py
esi_genoa_client/api/__init__.py
esi_genoa_client/api/alliance_api.py
esi_genoa_client/api/assets_api.py
esi_genoa_client/api/calendar_api.py
esi_genoa_client/api/character_api.py
esi_genoa_client/api/clones_api.py
esi_genoa_client/api/contacts_api.py
esi_genoa_client/api/contracts_api.py
esi_genoa_client/api/corporation_api.py
esi_genoa_client/api/corporation_projects_api.py
esi_genoa_client/api/dogma_api.py
esi_genoa_client/api/faction_warfare_api.py
esi_genoa_client/api/fittings_api.py
esi_genoa_client/api/fleets_api.py
esi_genoa_client/api/freelance_jobs_api.py
esi_genoa_client/api/incursions_api.py
esi_genoa_client/api/industry_api.py
esi_genoa_client/api/insurance_api.py
esi_genoa_client/api/killmails_api.py
esi_genoa_client/api/location_api.py
esi_genoa_client/api/loyalty_api.py
esi_genoa_client/api/mail_api.py
esi_genoa_client/api/market_api.py
esi_genoa_client/api/meta_api.py
esi_genoa_client/api/planetary_interaction_api.py
esi_genoa_client/api/routes_api.py
esi_genoa_client/api/search_api.py
esi_genoa_client/api/skills_api.py
esi_genoa_client/api/sovereignty_api.py
esi_genoa_client/api/status_api.py
esi_genoa_client/api/universe_api.py
esi_genoa_client/api/user_interface_api.py
esi_genoa_client/api/wallet_api.py
esi_genoa_client/api/wars_api.py
esi_genoa_client/models/__init__.py
esi_genoa_client/models/alliance_id.py
esi_genoa_client/models/alliances_alliance_id_contacts_get_inner.py
esi_genoa_client/models/alliances_alliance_id_contacts_labels_get_inner.py
esi_genoa_client/models/alliances_alliance_id_get.py
esi_genoa_client/models/alliances_alliance_id_icons_get.py
esi_genoa_client/models/boolean.py
esi_genoa_client/models/capture_fw_complex.py
esi_genoa_client/models/character_id.py
esi_genoa_client/models/characters_affiliation_post_inner.py
esi_genoa_client-0.1.2.dist-info/METADATA
esi_genoa_client-0.1.2.dist-info/WHEEL
esi_genoa_client-0.1.2.dist-info/top_level.txt
esi_genoa_client-0.1.2.dist-info/RECORD
