Metadata-Version: 2.4
Name: esi_genoa_client
Version: 0.1.2
Summary: EVE Stable Infrastructure (ESI) - tranquility
Home-page: https://github.com/Arcyfa/esi-genoa-client
Author: Arcyfa
Author-email: Arcyfa <arcyfa_github@pm.me>
License: EVE Developer License
Project-URL: Repository, https://github.com/Arcyfa/esi-genoa-client
Keywords: OpenAPI,OpenAPI-Generator,EVE Stable Infrastructure (ESI) - tranquility
Requires-Python: >=3.9
Requires-Dist: urllib3<3.0.0,>=2.1.0
Requires-Dist: python-dateutil>=2.8.2
Requires-Dist: pydantic>=2
Requires-Dist: typing-extensions>=4.7.1
Dynamic: author
Dynamic: home-page
